{
  "annotations": {
    "list": []
  },
  "editable": true,
  "fiscalYearStartMonth": 0,
  "graphTooltip": 0,
  "id": null,
  "links": [],
  "liveNow": false,
  "panels": [
    {
      "datasource": {
        "type": "influxdb",
        "uid": "InfluxDB-Awatch"
      },
      "description": "Reconstruction error over time from anomaly detection",
      "fieldConfig": {
        "defaults": {
          "color": { "mode": "palette-classic" },
          "custom": {
            "axisBorderShow": false,
            "axisCenteredZero": false,
            "axisColorMode": "text",
            "axisLabel": "",
            "axisPlacement": "auto",
            "barAlignment": 0,
            "drawStyle": "line",
            "fillOpacity": 0,
            "gradientMode": "none",
            "hideFrom": { "legend": false, "tooltip": false, "viz": false },
            "insertNulls": false,
            "lineInterpolation": "linear",
            "lineWidth": 1,
            "pointSize": 5,
            "scaleDistribution": { "type": "linear" },
            "showPoints": "never",
            "spanNulls": false,
            "stacking": { "group": "A", "mode": "none" },
            "thresholdsStyle": { "mode": "line" }
          },
          "mappings": [],
          "unit": "none"
        },
        "overrides": []
      },
      "gridPos": {
        "h": 8,
        "w": 12,
        "x": 0,
        "y": 0
      },
      "id": 1,
      "options": {
        "legend": { "calcs": [], "displayMode": "list", "placement": "bottom", "showLegend": true },
        "tooltip": { "mode": "multi", "sort": "none" }
      },
      "targets": [
        {
          "datasource": { "type": "influxdb", "uid": "InfluxDB-Awatch" },
          "query": "from(bucket: \"metrics\")\n  |> range(start: v.timeRangeStart, stop: v.timeRangeStop)\n  |> filter(fn: (r) => r._measurement == \"alerts\")\n  |> filter(fn: (r) => r._field == \"reconstruction_error\")\n  |> filter(fn: (r) => r.agent_id == \"${agent_id}\")\n  |> yield(name: \"reconstruction_error\")",
          "refId": "A"
        }
      ],
      "title": "Reconstruction Error Over Time",
      "type": "timeseries"
    },
    {
      "datasource": {
        "type": "influxdb",
        "uid": "InfluxDB-Awatch"
      },
      "description": "Alert threshold line",
      "fieldConfig": {
        "defaults": {
          "color": { "mode": "palette-classic" },
          "custom": {
            "axisBorderShow": false,
            "axisCenteredZero": false,
            "axisColorMode": "text",
            "axisLabel": "",
            "axisPlacement": "auto",
            "barAlignment": 0,
            "drawStyle": "line",
            "fillOpacity": 0,
            "gradientMode": "none",
            "hideFrom": { "legend": false, "tooltip": false, "viz": false },
            "insertNulls": false,
            "lineInterpolation": "linear",
            "lineWidth": 2,
            "pointSize": 5,
            "scaleDistribution": { "type": "linear" },
            "showPoints": "never",
            "spanNulls": false,
            "stacking": { "group": "A", "mode": "none" },
            "thresholdsStyle": { "mode": "off" }
          },
          "mappings": [],
          "unit": "none"
        },
        "overrides": []
      },
      "gridPos": {
        "h": 8,
        "w": 12,
        "x": 12,
        "y": 0
      },
      "id": 2,
      "options": {
        "legend": { "calcs": [], "displayMode": "list", "placement": "bottom", "showLegend": true },
        "tooltip": { "mode": "multi", "sort": "none" }
      },
      "targets": [
        {
          "datasource": { "type": "influxdb", "uid": "InfluxDB-Awatch" },
          "query": "from(bucket: \"metrics\")\n  |> range(start: v.timeRangeStart, stop: v.timeRangeStop)\n  |> filter(fn: (r) => r._measurement == \"alerts\")\n  |> filter(fn: (r) => r._field == \"threshold\")\n  |> filter(fn: (r) => r.agent_id == \"${agent_id}\")\n  |> aggregateWindow(every: v.windowPeriod, fn: mean, createEmpty: false)\n  |> yield(name: \"threshold\")",
          "refId": "A"
        }
      ],
      "title": "Alert Threshold",
      "type": "timeseries"
    },
    {
      "datasource": {
        "type": "influxdb",
        "uid": "InfluxDB-Awatch"
      },
      "description": "Distribution of alerts by severity level",
      "fieldConfig": {
        "defaults": {
          "color": { "mode": "palette-classic" },
          "custom": {
            "hideFrom": { "legend": false, "tooltip": false, "viz": false }
          },
          "mappings": [],
          "unit": "none"
        },
        "overrides": []
      },
      "gridPos": {
        "h": 8,
        "w": 12,
        "x": 0,
        "y": 8
      },
      "id": 3,
      "options": {
        "legend": { "displayMode": "list", "placement": "right", "showLegend": true },
        "pieType": "pie",
        "reduceOptions": {
          "calcs": ["lastNotNull"],
          "fields": "",
          "values": false
        },
        "tooltip": { "mode": "single", "sort": "none" }
      },
      "targets": [
        {
          "datasource": { "type": "influxdb", "uid": "InfluxDB-Awatch" },
          "query": "from(bucket: \"metrics\")\n  |> range(start: v.timeRangeStart, stop: v.timeRangeStop)\n  |> filter(fn: (r) => r._measurement == \"alerts\")\n  |> filter(fn: (r) => r._field == \"confidence\")\n  |> group(columns: [\"severity\"])\n  |> count()\n  |> yield(name: \"count\")",
          "refId": "A"
        }
      ],
      "title": "Alert Count by Severity",
      "type": "piechart"
    },
    {
      "datasource": {
        "type": "influxdb",
        "uid": "InfluxDB-Awatch"
      },
      "description": "Table of recent alert events",
      "fieldConfig": {
        "defaults": {
          "color": { "mode": "thresholds" },
          "custom": {
            "align": "auto",
            "cellOptions": { "type": "auto" },
            "inspect": false
          },
          "mappings": [],
          "thresholds": { "mode": "absolute", "steps": [{ "color": "green", "value": null }] }
        },
        "overrides": []
      },
      "gridPos": {
        "h": 8,
        "w": 12,
        "x": 12,
        "y": 8
      },
      "id": 4,
      "options": {
        "cellHeight": "sm",
        "footer": { "countRows": false, "fields": "", "reducer": ["sum"], "show": false },
        "showHeader": true
      },
      "targets": [
        {
          "datasource": { "type": "influxdb", "uid": "InfluxDB-Awatch" },
          "query": "from(bucket: \"metrics\")\n  |> range(start: v.timeRangeStart, stop: v.timeRangeStop)\n  |> filter(fn: (r) => r._measurement == \"alerts\")\n  |> pivot(rowKey: [\"_time\", \"agent_id\", \"severity\"], columnKey: [\"_field\"], valueColumn: \"_value\")\n  |> sort(columns: [\"_time\"], desc: true)\n  |> limit(n: 100)",
          "refId": "A"
        }
      ],
      "title": "Alert Timeline",
      "type": "table"
    }
  ],
  "refresh": "30s",
  "schemaVersion": 38,
  "tags": ["awatch", "anomaly"],
  "templating": {
    "list": [
      {
        "current": {},
        "datasource": {
          "type": "influxdb",
          "uid": "InfluxDB-Awatch"
        },
        "definition": "import \"influxdata/influxdb/schema\"\nschema.tagValues(bucket: \"metrics\", tag: \"agent_id\")",
        "hide": 0,
        "includeAll": false,
        "multi": false,
        "name": "agent_id",
        "options": [],
        "query": "import \"influxdata/influxdb/schema\"\nschema.tagValues(bucket: \"metrics\", tag: \"agent_id\")",
        "refresh": 1,
        "regex": "",
        "skipUrlSync": false,
        "sort": 1,
        "type": "query"
      }
    ]
  },
  "time": {
    "from": "now-6h",
    "to": "now"
  },
  "timepicker": {},
  "timezone": "",
  "title": "Awatch - Anomaly Analysis",
  "uid": "awatch-anomaly-analysis",
  "version": 1,
  "weekStart": ""
}
